LICENSE
README.md
pyproject.toml
setup.py
mustasa.egg-info/PKG-INFO
mustasa.egg-info/SOURCES.txt
mustasa.egg-info/dependency_links.txt
mustasa.egg-info/requires.txt
mustasa.egg-info/top_level.txt
src/mustasa/__init__.py
src/mustasa/asyncio.py
src/mustasa/connect.py
src/mustasa/functions.py