Metadata-Version: 2.1
Name: mustasa
Version: 1.1.0
Summary: SQL Database Wrapper
Home-page: https://github.com/joumaico/mustasa
Author: Joumaico Maulas
Author-email: joumaico@yahoo.com
Classifier: Development Status :: 5 - Production/Stable
Classifier: License :: OSI Approved :: GNU General Public License v3 (GPLv3)
Classifier: Operating System :: OS Independent
Classifier: Programming Language :: Python :: 3.11
Classifier: Programming Language :: Python :: 3.12
Requires-Python: >=3.11
License-File: LICENSE
